fletable/__init__.py
fletable/editable_table.py
fletable/sql_table.py
fletable/utils.py
fletable-0.0.3.dist-info/METADATA
fletable-0.0.3.dist-info/WHEEL
fletable-0.0.3.dist-info/top_level.txt
fletable-0.0.3.dist-info/RECORD
