Metadata-Version: 2.4
Name: fletable
Version: 0.0.3
Summary: Tables that take data from SQL database
Home-page: https://github.com/RichCake/fletable
Author: RichCake
Author-email: abs2016123@gmail.com
Project-URL: GitHub, https://github.com/RichCake/fletable
Keywords: flet sql table
Classifier: Programming Language :: Python :: 3.12
Classifier: License :: OSI Approved :: MIT License
Classifier: Operating System :: OS Independent
Requires-Python: >=3.9
Requires-Dist: flet==0.28.3
Requires-Dist: flet-cli==0.28.3
Requires-Dist: flet-desktop==0.28.3
Requires-Dist: flet-web==0.28.3
Dynamic: author
Dynamic: author-email
Dynamic: classifier
Dynamic: description
Dynamic: description-content-type
Dynamic: home-page
Dynamic: keywords
Dynamic: project-url
Dynamic: requires-dist
Dynamic: requires-python
Dynamic: summary
